zxext/.gitattributes
zxext/.gitignore
zxext/README.md
zxext/UPDATE.txt
zxext/Url.py
zxext/__init__.py
zxext/models.py
zxext/workbook.py
zxext/.vscode/settings.json
zxext-0.1.2.dist-info/METADATA
zxext-0.1.2.dist-info/WHEEL
zxext-0.1.2.dist-info/licenses/LICENSE
zxext-0.1.2.dist-info/RECORD
