Metadata-Version: 2.1
Name: zxext
Version: 0.1.2
Summary: zhixuewang库的扩展包
Project-URL: Homepage, https://github.com/MasterYuan418/zxext
Project-URL: Bug Tracker, https://github.com/MasterYuan418/zxext/issues
Author: MasterYuan418
License-File: LICENSE
Classifier: Operating System :: OS Independent
Classifier: Programming Language :: Python :: 3
Requires-Python: >=3.8
